podao/cli.py
podao/constant.py
podao/main.py
podao/util.py
podao-0.8.2.dist-info/LICENSE
podao-0.8.2.dist-info/METADATA
podao-0.8.2.dist-info/WHEEL
podao-0.8.2.dist-info/entry_points.txt
podao-0.8.2.dist-info/top_level.txt
podao-0.8.2.dist-info/RECORD
