Metadata-Version: 2.1
Name: podao
Version: 0.8.2
Summary: A python project environment build tool.
Author-email: Li zhigang <imlzg@126.com>
License: MIT License
Project-URL: Homepage, https://github.com/liangshanpo/podao
Project-URL: Bug Tracker, https://github.com/liangshanpo/podao/issues
Keywords: environment,dependency,workflow
Classifier: Development Status :: 5 - Production/Stable
Classifier: Intended Audience :: Developers
Classifier: Topic :: Software Development :: Build Tools
Classifier: License :: OSI Approved :: MIT License
Classifier: Operating System :: OS Independent
Classifier: Programming Language :: Python
Classifier: Programming Language :: Python :: 3 :: Only
Classifier: Programming Language :: Python :: 3.10
Classifier: Programming Language :: Python :: 3.11
Requires-Python: >=3.10
License-File: LICENSE
Requires-Dist: pip
Requires-Dist: sh
Requires-Dist: click
Requires-Dist: tomlkit
Requires-Dist: packaging
Provides-Extra: dev
Requires-Dist: black ; extra == 'dev'
Requires-Dist: isort ; extra == 'dev'
Requires-Dist: pytest ; extra == 'dev'
Requires-Dist: pytest-depends ; extra == 'dev'
